aioelectricitymaps/__init__.py
aioelectricitymaps/const.py
aioelectricitymaps/electricitymaps.py
aioelectricitymaps/exceptions.py
aioelectricitymaps/models/__init__.py
aioelectricitymaps/models/carbon_intensity.py
aioelectricitymaps/models/home_assistant.py
aioelectricitymaps/models/power_breakdown.py
aioelectricitymaps/models/zone.py
aioelectricitymaps/py.typed
aioelectricitymaps/request.py
aioelectricitymaps-1.1.1.dist-info/LICENSE
aioelectricitymaps-1.1.1.dist-info/METADATA
aioelectricitymaps-1.1.1.dist-info/WHEEL
aioelectricitymaps-1.1.1.dist-info/RECORD
