Metadata-Version: 2.3
Name: aioelectricitymaps
Version: 1.1.1
Summary: Async Python 3 wrapper for Electricity maps
License: MIT
Author: Jan-Philipp Benecke
Author-email: jan-philipp@bnck.me
Requires-Python: >=3.11,<4.0
Classifier: Development Status :: 5 - Production/Stable
Classifier: Framework :: AsyncIO
Classifier: Intended Audience :: Developers
Classifier: License :: OSI Approved :: MIT License
Classifier: Natural Language :: English
Classifier: Programming Language :: Python :: 3
Classifier: Programming Language :: Python :: 3.11
Classifier: Programming Language :: Python :: 3.12
Classifier: Programming Language :: Python :: 3.13
Classifier: Topic :: Software Development :: Libraries :: Python Modules
Requires-Dist: aiohttp (>=3.8.0)
Requires-Dist: mashumaro (>=3.11)
Requires-Dist: orjson (>=3.9.8)
Project-URL: Bug Tracker, https://github.com/jpbede/aioelectricitymaps/issues
Project-URL: Changelog, https://github.com/jpbede/aioelectricitymaps/releases
Project-URL: Repository, https://github.com/jpbede/aioelectricitymaps
